pckgr/__init__.py
pckgr/__main__.py
pckgr/utilities/__init__.py
pckgr/utilities/cliUtilities.py
pckgr/utilities/configUtilities.py
pckgr/utilities/errorCodes.py
pckgr/utilities/fileUtilities.py
pckgr/utilities/packageInitialiser.py
pckgr/utilities/pathFinder.py
pckgr/utilities/test.py
pckgr/utilities/toolsUtilities.py
pckgr/utilities/validationUtilities.py
pckgr-1.0.0.dist-info/licenses/LICENSE
pckgr-1.0.0.dist-info/METADATA
pckgr-1.0.0.dist-info/WHEEL
pckgr-1.0.0.dist-info/entry_points.txt
pckgr-1.0.0.dist-info/top_level.txt
pckgr-1.0.0.dist-info/RECORD
