Metadata-Version: 2.4
Name: pckgr
Version: 1.0.0
Author: Nichola Walch
Author-email: Nichola Walch <littler.compression@gmail.com>
License: MIT License
Requires-Python: >=3.8
License-File: LICENSE
Requires-Dist: numpy
Requires-Dist: toml
Requires-Dist: noexcept
Dynamic: author
Dynamic: license-file
Dynamic: requires-python
